complex_mathematics/__init__.py
complex_mathematics/algebra.py
complex_mathematics/calculus.py
complex_mathematics/complex.py
complex_mathematics/linalg.py
complex_mathematics/ml.py
complex_mathematics/stats.py
complex_mathematics-4.17.10.dist-info/LICENSE
complex_mathematics-4.17.10.dist-info/METADATA
complex_mathematics-4.17.10.dist-info/WHEEL
complex_mathematics-4.17.10.dist-info/top_level.txt
complex_mathematics-4.17.10.dist-info/RECORD
