Metadata-Version: 2.1
Name: complex-mathematics
Version: 4.17.10
Summary: Many complex math features.
Home-page: https://github.com/Arnav-MaIhotra/complex_mathematics
Author: Arnav Malhotra
Author-email: emumalhotra@gmail.com
License: MIT
License-File: LICENSE
Requires-Dist: numpy
Requires-Dist: scipy
Requires-Dist: matplotlib
